pycharm_debug.py
pycharm_debug-0.4.0.dist-info/METADATA
pycharm_debug-0.4.0.dist-info/WHEEL
pycharm_debug-0.4.0.dist-info/top_level.txt
pycharm_debug-0.4.0.dist-info/RECORD
