Metadata-Version: 2.1
Name: pycharm_debug
Version: 0.4.0
Summary: Connection helper for PyCharm Python Remote Debugging.
Home-page: https://github.com/ldunham1/pycharm_debug
Author: Lee Dunham
Author-email: leedunham@gmail.com
License: MIT
Classifier: Intended Audience :: Developers
Classifier: License :: OSI Approved :: MIT License
Classifier: Programming Language :: Python
Classifier: Programming Language :: Python :: 2.7
Classifier: Programming Language :: Python :: 3
Classifier: Operating System :: OS Independent
Classifier: Topic :: Software Development :: Libraries :: Python Modules
Classifier: Topic :: Utilities
